onepass_env/__about__.py
onepass_env/__init__.py
onepass_env/cli.py
onepass_env/config.py
onepass_env/core.py
onepass_env/exceptions.py
onepass_env/onepassword.py
onepass_env/validation.py
1pass_env-0.1.0.dist-info/METADATA
1pass_env-0.1.0.dist-info/WHEEL
1pass_env-0.1.0.dist-info/entry_points.txt
1pass_env-0.1.0.dist-info/licenses/LICENSE
1pass_env-0.1.0.dist-info/RECORD
